odoo10_addon_bank_statement_foreign_currency-10.0.1.0.0-py2.7-nspkg.pth
odoo/addons/bank_statement_foreign_currency/README.rst
odoo/addons/bank_statement_foreign_currency/__init__.py
odoo/addons/bank_statement_foreign_currency/__manifest__.py
odoo/addons/bank_statement_foreign_currency/static/description/icon.png
odoo/addons/bank_statement_foreign_currency/views/account_view.xml
odoo10_addon_bank_statement_foreign_currency-10.0.1.0.0.dist-info/DESCRIPTION.rst
odoo10_addon_bank_statement_foreign_currency-10.0.1.0.0.dist-info/METADATA
odoo10_addon_bank_statement_foreign_currency-10.0.1.0.0.dist-info/RECORD
odoo10_addon_bank_statement_foreign_currency-10.0.1.0.0.dist-info/WHEEL
odoo10_addon_bank_statement_foreign_currency-10.0.1.0.0.dist-info/metadata.json
odoo10_addon_bank_statement_foreign_currency-10.0.1.0.0.dist-info/namespace_packages.txt
odoo10_addon_bank_statement_foreign_currency-10.0.1.0.0.dist-info/top_level.txt
